__init__.py
main.py
utils/__init__.py
utils/helper.py
validator/__init__.py
validator/validator.py
validator/validator_report.py
vault_appsettings_linter-1.0.3.dist-info/METADATA
vault_appsettings_linter-1.0.3.dist-info/WHEEL
vault_appsettings_linter-1.0.3.dist-info/entry_points.txt
vault_appsettings_linter-1.0.3.dist-info/top_level.txt
vault_appsettings_linter-1.0.3.dist-info/RECORD
