Metadata-Version: 2.4
Name: vault-appsettings-linter
Version: 1.0.3
Summary: Stratio Appsettings files linter for compatibility with Stratio.Extensions.Configuration.Vault
Author-email: Stratio Automotive <devops@stratioautomotive.com>, Rafael Couto <rafaelcouto@stratioautomotive.com>, Bernardo Marques <bernardomarques@stratioautomotive.com>
Maintainer-email: Rafael Couto <rafaelcouto@stratioautomotive.com>, Bernardo Marques <bernardomarques@stratioautomotive.com>
License: # GNU LESSER GENERAL PUBLIC LICENSE
Project-URL: Repository, https://github.com/stratio-automotive/Stratio.Extensions.Configuration.Vault
Project-URL: Stratio Automotive, https://www.stratioautomotive.com
Keywords: hashicorp,vault,appsettings,linter,stratio,.NET,dotnet
Classifier: Environment :: Console
Classifier: Programming Language :: Python :: 3.10
Classifier: License :: OSI Approved :: GNU Lesser General Public License v3 (LGPLv3)
Classifier: Operating System :: OS Independent
Classifier: Intended Audience :: Developers
Requires-Python: >=3.10
Requires-Dist: rich
Requires-Dist: validators
